nextcord_ormar/__init__.py
nextcord_ormar/models.py
nextcord_ormar/nxalembic/__init__.py
nextcord_ormar/nxalembic/exceptions.py
nextcord_ormar/nxalembic/parser.py
nextcord_ormar/nxalembic/template/env.py
nextcord_ormar/nxalembic/template/script.py.mako
nextcord_ormar-0.3.3.dist-info/entry_points.txt
nextcord_ormar-0.3.3.dist-info/LICENSE
nextcord_ormar-0.3.3.dist-info/WHEEL
nextcord_ormar-0.3.3.dist-info/METADATA
nextcord_ormar-0.3.3.dist-info/RECORD
